django_xsl_templates/__init__.py
django_xsl_templates-0.0.1.dev0.dist-info/METADATA
django_xsl_templates-0.0.1.dev0.dist-info/WHEEL
django_xsl_templates-0.0.1.dev0.dist-info/RECORD
